thin_plate_spline-1.2.0.dist-info/licenses/LICENSE
tps/__init__.py
tps/polynomial_transform.py
tps/py.typed
tps/thin_plate_spline.py
thin_plate_spline-1.2.0.dist-info/METADATA
thin_plate_spline-1.2.0.dist-info/WHEEL
thin_plate_spline-1.2.0.dist-info/top_level.txt
thin_plate_spline-1.2.0.dist-info/RECORD
